LICENSE
MANIFEST.in
README.md
requirements.txt
setup.cfg
setup.py
moltools/__init__.py
moltools/builder.py
moltools/dstruct.py
moltools/generator.py
moltools/molecules.py
moltools/pdbreader.py
moltools/plot_functions.py
moltools/polymer.py
moltools/property.py
moltools/read_dal.py
moltools/rotator.py
moltools/template.py
moltools/use_calculator.py
moltools/utilz.py
moltools.egg-info/PKG-INFO
moltools.egg-info/SOURCES.txt
moltools.egg-info/dependency_links.txt
moltools.egg-info/requires.txt
moltools.egg-info/top_level.txt
moltools/test/__init__.py
moltools/test/test_atom.py
moltools/test/test_attach_properties.py
moltools/test/test_bonds.py
moltools/test/test_cell.py
moltools/test/test_cluster.py
moltools/test/test_euler.py
moltools/test/test_mfcc.py
moltools/test/test_molecules.py
moltools/test/test_ofilter.py
moltools/test/test_property.py
moltools/test/test_read_dal.py
moltools/test/test_rotation.py
moltools/test/test_system.py
moltools/test/test_use_generator.py
moltools/test/test_utilz.py
moltools/test/test_various.py
moltools/test/pdbreader_tests/__init__.py
moltools/test/pdbreader_tests/concaps_level1.py
moltools/test/pdbreader_tests/concaps_level2.py
moltools/test/pdbreader_tests/cro_read_pdb.py
moltools/test/pdbreader_tests/cro_residues_level1.py
moltools/test/pdbreader_tests/cro_residues_level2.py
moltools/test/pdbreader_tests/read_pdb.py
moltools/test/pdbreader_tests/residues_level1.py
moltools/test/pdbreader_tests/residues_level2.py
moltools/test/pdbreader_tests/test_collagen.py
moltools/test/pdbreader_tests/test_pdbreader.py
moltools/test/pdbreader_tests/test_ppg.py
moltools/test/pdbreader_tests/test_ppg_level2.py
moltools/test/pdbreader_tests/test_ppg_level3.py
moltools/test/pdbreader_tests/test_property.py
moltools/test/pdbreader_tests/test_read_pdb.py
moltools/test/pdbreader_tests/test_system.py