Metadata-Version: 1.0
Name: moltools
Version: 1.1.1
Summary: Running point dipole calculations on chemical systems
Home-page: https://github.org/fishstamp82/moltools.git
Author: Ignat Harczuk
Author-email: ignathe@gmail.com
License: MIT
Platform: Linux
